fanoutqa/__init__.py
fanoutqa/models.py
fanoutqa/norm.py
fanoutqa/retrieval.py
fanoutqa/utils.py
fanoutqa/wiki.py
fanoutqa/data/LICENSE
fanoutqa/data/fanout-final-dev.json
fanoutqa/data/fanout-final-test.json
fanoutqa/eval/__init__.py
fanoutqa/eval/llm.py
fanoutqa/eval/models.py
fanoutqa/eval/scorer.py
fanoutqa/eval/string.py
fanoutqa/eval/utils.py
fanoutqa-1.1.1.dist-info/METADATA
fanoutqa-1.1.1.dist-info/WHEEL
fanoutqa-1.1.1.dist-info/licenses/LICENSE
fanoutqa-1.1.1.dist-info/RECORD
