Metadata-Version: 2.3
Name: fanoutqa
Version: 1.1.1
Summary: The companion code for the FanOutQA dataset + benchmark for LLMs.
Project-URL: Homepage, https://github.com/zhudotexe/fanoutqa
Project-URL: Bug Tracker, https://github.com/zhudotexe/fanoutqa/issues
Author-email: Andrew Zhu <andrew@zhu.codes>, Alyssa Hwang <ahwang16@seas.upenn.edu>, Liam Dugan <ldugan@seas.upenn.edu>
License: MIT License
License-File: LICENSE
Classifier: Intended Audience :: Science/Research
Classifier: License :: OSI Approved :: MIT License
Classifier: Operating System :: OS Independent
Classifier: Programming Language :: Python :: 3
Classifier: Topic :: Scientific/Engineering :: Artificial Intelligence
Requires-Python: >=3.8
Requires-Dist: ftfy<=7.0.0,>=6.1.3
Requires-Dist: httpx<1.0.0,>=0.26.0
Requires-Dist: markdownify~=0.11.6
Requires-Dist: spacy<4.0.0,>=3.7.2
Provides-Extra: all
Requires-Dist: kani[openai]<2.0.0,>=1.0.0rc0; extra == 'all'
Requires-Dist: rank-bm25~=0.2.2; extra == 'all'
Requires-Dist: rouge-score~=0.1.2; extra == 'all'
Provides-Extra: eval
Requires-Dist: kani[openai]<2.0.0,>=1.0.0rc0; extra == 'eval'
Requires-Dist: rouge-score~=0.1.2; extra == 'eval'
Provides-Extra: retrieval
Requires-Dist: rank-bm25~=0.2.2; extra == 'retrieval'
